{
    "NodeSystem.Add": {
        "request": "com.type.json"
    },
    "NodeSystem.Del": {
        "request": "com.type.json"
    },
    "NodeSystem.Find": {
        "response": "com.type.json"
    },
    "NodeSystem.Ping": {

    },
    "NodeSystem.Hotfix": {

    },
    "NodeSystem.SetLogLevel" : {
        "request" : "com.type.int32"
    },
    "NodeSystem.RunInfo": {
        "async":true,
        "response": "com.type.json"
    },
    "NodeSystem.Shutdown": {
        "async":true
    },
    "NodeSystem.LoadConfig": {

    }
}